CHANGELOG.md
MANIFEST.in
README.rst
setup.cfg
setup.py
django_groupadmin_users.egg-info/PKG-INFO
django_groupadmin_users.egg-info/SOURCES.txt
django_groupadmin_users.egg-info/dependency_links.txt
django_groupadmin_users.egg-info/top_level.txt
groupadmin_users/__init__.py
groupadmin_users/admin.py
groupadmin_users/forms.py
groupadmin_users/locale/ca/LC_MESSAGES/django.mo
groupadmin_users/locale/ca/LC_MESSAGES/django.po
groupadmin_users/locale/es/LC_MESSAGES/django.mo
groupadmin_users/locale/es/LC_MESSAGES/django.po